authboot/__init__.py
authboot/apps.py
authboot/utils.py
authboot/__pycache__/__init__.cpython-313.pyc
authboot/__pycache__/apps.cpython-313.pyc
authboot/__pycache__/utils.cpython-313.pyc
authboot/management/commands/create_user.py
authboot/management/commands/__pycache__/create_user.cpython-313.pyc
dStats/__init__.py
dStats/asgi.py
dStats/server.py
dStats/settings.py
dStats/urls.py
dStats/views.py
dStats/__pycache__/__init__.cpython-313.pyc
dStats/__pycache__/asgi.cpython-313.pyc
dStats/__pycache__/settings.cpython-313.pyc
dStats/__pycache__/urls.cpython-313.pyc
dStats/__pycache__/views.cpython-313.pyc
dStats/templates/dStats/index.html
dstats-1.0.7.dist-info/licenses/LICENSE
dstats-1.0.7.dist-info/METADATA
dstats-1.0.7.dist-info/WHEEL
dstats-1.0.7.dist-info/entry_points.txt
dstats-1.0.7.dist-info/top_level.txt
dstats-1.0.7.dist-info/RECORD
